pytl/__init__.py
pytl/pytl.py
pytl-0.2.4.dist-info/DESCRIPTION.rst
pytl-0.2.4.dist-info/METADATA
pytl-0.2.4.dist-info/RECORD
pytl-0.2.4.dist-info/WHEEL
pytl-0.2.4.dist-info/entry_points.txt
pytl-0.2.4.dist-info/metadata.json
pytl-0.2.4.dist-info/top_level.txt
test/__init__.py
test/person.py
test/test.py
