Metadata-Version: 2.0
Name: pytl
Version: 0.2.4
Summary: Command line tool that parses python file, enumerates classes and methods as a tree structure.
Home-page: https://github.com/ryo-ma/pytl
Author: ryo-ma
Author-email: saka_ro@yahoo.co.jp
License: MIT
Download-URL: https://github.com/ryo-ma/pytl
Keywords: Python file structure tree line
Platform: any
Classifier: Environment :: Console
Classifier: Intended Audience :: End Users/Desktop
Classifier: Programming Language :: Python :: 2.7
Classifier: Programming Language :: Python :: 3.6
Classifier: Programming Language :: Python :: 3.5
Classifier: Programming Language :: Python :: 3.4
Classifier: Programming Language :: Python :: 3.3
Classifier: License :: OSI Approved :: MIT License
